lqmt/LQMT.py
lqmt/__init__.py
lqmt/main.py
lqmt/lqm/__init__.py
lqmt/lqm/config.py
lqmt/lqm/controller.py
lqmt/lqm/data.py
lqmt/lqm/exceptions.py
lqmt/lqm/logging.py
lqmt/lqm/processed.py
lqmt/lqm/sourcedir.py
lqmt/lqm/sourcefilter.py
lqmt/lqm/sources.py
lqmt/lqm/systemconfig.py
lqmt/lqm/tool.py
lqmt/lqm/unprocessed.py
lqmt/lqm/parsers/__init__.py
lqmt/lqm/parsers/FlexTransform/__init__.py
lqmt/lqm/parsers/FlexTransform/parser.py
lqmt/lqm/parsers/RuleParser/__init__.py
lqmt/lqm/parsers/RuleParser/parser.py
lqmt/lqm/parsers/STIXParser/__init__.py
lqmt/lqm/parsers/STIXParser/parser.py
lqmt/test/__init__.py
lqmt/test/configuration_test.py
lqmt/test/filter_test.py
lqmt/test/parser_test.py
lqmt/test/ruleparser_test.py
lqmt/test/stixparser_test.py
lqmt/test/whitelist_test.py
lqmt/test/test_data/__init__.py
lqmt/test/test_data/sample_config.py
lqmt/test/test_data/sample_inputs.py
lqmt/test/test_data/filters/__init__.py
lqmt/test/test_data/filters/filter_configs.py
lqmt/test/test_data/filters/filter_inputs.py
lqmt/tools/__init__.py
lqmt/tools/from_snort/__init__.py
lqmt/tools/from_snort/config.py
lqmt/tools/from_snort/tool.py
lqmt/tools/to_arcsight/__init__.py
lqmt/tools/to_arcsight/config.py
lqmt/tools/to_arcsight/tool.py
lqmt/tools/to_bro/__init__.py
lqmt/tools/to_bro/config.py
lqmt/tools/to_bro/tool.py
lqmt/tools/to_cef/__init__.py
lqmt/tools/to_cef/config.py
lqmt/tools/to_cef/tool.py
lqmt/tools/to_checkpoint/__init__.py
lqmt/tools/to_checkpoint/config.py
lqmt/tools/to_checkpoint/rc.py
lqmt/tools/to_checkpoint/tool.py
lqmt/tools/to_csv/__init__.py
lqmt/tools/to_csv/config.py
lqmt/tools/to_csv/tool.py
lqmt/tools/to_flextext/__init__.py
lqmt/tools/to_flextext/config.py
lqmt/tools/to_flextext/tool.py
lqmt/tools/to_mbl/__init__.py
lqmt/tools/to_mbl/config.py
lqmt/tools/to_mbl/tool.py
lqmt/tools/to_paloalto/__init__.py
lqmt/tools/to_paloalto/config.py
lqmt/tools/to_paloalto/tool.py
lqmt-1.4.3.dist-info/METADATA
lqmt-1.4.3.dist-info/RECORD
lqmt-1.4.3.dist-info/WHEEL
lqmt-1.4.3.dist-info/entry_points.txt
lqmt-1.4.3.dist-info/top_level.txt
