Metadata-Version: 2.1
Name: lqmt
Version: 1.4.3
Summary: Flexible framework that allows automation to process cyber threat information and update endpoint defense tools
Home-page: https://github.com/anl-cyberscience/LQMToolset/
Author: The CFM Team
Author-email: fedhelp@anl.gov
License: UNKNOWN
Keywords: firewall endpoint last quarter mile toolset palo alto syslog checkpoint flextext
Platform: UNKNOWN
Classifier: Development Status :: 4 - Beta
Classifier: Intended Audience :: Information Technology
Classifier: Topic :: Security
Classifier: License :: Other/Proprietary License
Classifier: Programming Language :: Python :: 3
Classifier: Programming Language :: Python :: 3.2
Classifier: Programming Language :: Python :: 3.3
Classifier: Programming Language :: Python :: 3.4
Classifier: Programming Language :: Python :: 3.5
Classifier: Programming Language :: Python :: 3.6
Requires-Dist: lxml
Requires-Dist: netaddr
Requires-Dist: pan-python
Requires-Dist: toml
Requires-Dist: FlexTransform (>=1.2.1)
Requires-Dist: requests
Requires-Dist: arrow
Requires-Dist: stix
Requires-Dist: stix-ramrod
Requires-Dist: jsonpath-rw
Requires-Dist: pyshark
Requires-Dist: pyparsing
Requires-Dist: idstools
Requires-Dist: xmltodict
